aiodataloader.py
aiodataloader_next-0.1.4.dist-info/LICENSE
aiodataloader_next-0.1.4.dist-info/METADATA
aiodataloader_next-0.1.4.dist-info/WHEEL
aiodataloader_next-0.1.4.dist-info/top_level.txt
aiodataloader_next-0.1.4.dist-info/RECORD
