Metadata-Version: 2.1
Name: aiodataloader-next
Version: 0.1.4
Summary: Asyncio DataLoader implementation for Python
Home-page: https://github.com/syrusakbary/aiodataloader
Author: Syrus Akbary, The AIODataLoader contributors
Author-email: me@syrusakbary.com, zinsouloris@gmail.com
License: MIT
Download-URL: https://github.com/syrusakbary/aiodataloader/releases
Keywords: concurrent future deferred aiodataloader
Platform: UNKNOWN
Classifier: Development Status :: 5 - Production/Stable
Classifier: Intended Audience :: Developers
Classifier: Topic :: Software Development :: Libraries
Classifier: Programming Language :: Python :: 3
Classifier: Programming Language :: Python :: 3.5
Classifier: Programming Language :: Python :: 3.6
Classifier: Programming Language :: Python :: 3.7
Classifier: License :: OSI Approved :: MIT License
Provides-Extra: test
Requires-Dist: pytest (>=3.6) ; extra == 'test'
Requires-Dist: pytest-cov ; extra == 'test'
Requires-Dist: coveralls ; extra == 'test'
Requires-Dist: mock ; extra == 'test'
Requires-Dist: pytest-asyncio ; extra == 'test'
